{"content": {"suites": {"0": {"status": {"total_pass": 3, "total_skip": 0, "total_xpass": 0, "total_xfail": 0, "total_rerun": 0, "total_fail": 0, "total_error": 1}, "tests": {"0": {"status": "ERROR", "message": "file /Users/monster/PycharmProjects/TestFramework/TestCase/step2.py, line 14\n  def test_step_decorator(func):\nE       fixture 'func' not found\n>       available fixtures: add_action, add_custom_timestamp, cache, capfd, capfdbinary, caplog, capsys, capsysbinary, custom_report, doctest_namespace, extra, include_metadata_in_junit_xml, metadata, monkeypatch, pytestconfig, record_property, record_testsuite_property, record_xml_attribute, recwarn, timestamp, tmp_path, tmp_path_factory, tmpdir, tmpdir_factory\n>       use 'pytest --fixtures [testpath]' for help on them.\n\n/Users/monster/PycharmProjects/TestFramework/TestCase/step2.py:14\n", "test_name": "test_step_decorator", "rerun": "0"}, "1": {"status": "PASS", "message": "", "test_name": "test_example[Click button-Button is visible-Button is visible-PASS]", "rerun": "0"}, "2": {"status": "PASS", "message": "", "test_name": "test_example[Fill out form-Form submitted successfully-Form submission failed-FAILED]", "rerun": "0"}, "3": {"status": "PASS", "message": "", "test_name": "test_example[Verify data-Data comparison-TBD-TBD]", "rerun": "0"}}, "suite_name": "step2.py"}}}, "date": "May 28, 2023", "start_time": 1685234873.22843, "total_suite": 1, "status": "FAIL", "status_list": {"pass": "3", "fail": "0", "skip": "0", "error": "1", "xpass": "0", "xfail": "0", "rerun": "0"}, "total_tests": "4"}